mongodb_logger/__init__.py
mongodb_logger/handler.py
mongodb_logger/py.typed
mongodb_logger-0.1.0.dist-info/METADATA
mongodb_logger-0.1.0.dist-info/WHEEL
mongodb_logger-0.1.0.dist-info/licenses/LICENSE
mongodb_logger-0.1.0.dist-info/RECORD
