Metadata-Version: 2.4
Name: mongodb-logger
Version: 0.1.0
Summary: Intelligent MongoDB logging handler for Python with structured data support
Project-URL: Homepage, https://github.com/miroblog/mongodb-logger
Project-URL: Documentation, https://github.com/miroblog/mongodb-logger#readme
Project-URL: Repository, https://github.com/miroblog/mongodb-logger.git
Project-URL: Bug Tracker, https://github.com/miroblog/mongodb-logger/issues
Author-email: MongoDB Logger Team <support@example.com>
Maintainer-email: MongoDB Logger Team <support@example.com>
License: MIT License
License-File: LICENSE
Keywords: database-logging,json-logging,logging,mongodb,python-logging,structured-logging
Classifier: Development Status :: 4 - Beta
Classifier: Intended Audience :: Developers
Classifier: License :: OSI Approved :: MIT License
Classifier: Operating System :: OS Independent
Classifier: Programming Language :: Python :: 3
Classifier: Programming Language :: Python :: 3.8
Classifier: Programming Language :: Python :: 3.9
Classifier: Programming Language :: Python :: 3.10
Classifier: Programming Language :: Python :: 3.11
Classifier: Programming Language :: Python :: 3.12
Classifier: Topic :: Database
Classifier: Topic :: Software Development :: Libraries :: Python Modules
Classifier: Topic :: System :: Logging
Requires-Python: >=3.8
Requires-Dist: pymongo>=4.0.0
Requires-Dist: python-dotenv>=1.0.0
Provides-Extra: dev
Requires-Dist: black>=23.0.0; extra == 'dev'
Requires-Dist: flake8>=6.0.0; extra == 'dev'
Requires-Dist: isort>=5.12.0; extra == 'dev'
Requires-Dist: mypy>=1.0.0; extra == 'dev'
Requires-Dist: pre-commit>=3.0.0; extra == 'dev'
Requires-Dist: pytest-cov>=4.0.0; extra == 'dev'
Requires-Dist: pytest>=7.0.0; extra == 'dev'
Provides-Extra: test
Requires-Dist: pytest-cov>=4.0.0; extra == 'test'
Requires-Dist: pytest-mock>=3.10.0; extra == 'test'
Requires-Dist: pytest>=7.0.0; extra == 'test'
